adafruit_connection_manager.py
adafruit_circuitpython_connectionmanager-1.0.0.dist-info/LICENSE
adafruit_circuitpython_connectionmanager-1.0.0.dist-info/METADATA
adafruit_circuitpython_connectionmanager-1.0.0.dist-info/WHEEL
adafruit_circuitpython_connectionmanager-1.0.0.dist-info/top_level.txt
adafruit_circuitpython_connectionmanager-1.0.0.dist-info/RECORD
