Metadata-Version: 2.1
Name: adafruit-circuitpython-connectionmanager
Version: 1.0.0
Summary: A urllib3.poolmanager/urllib3.connectionpool-like library for managing sockets and connections
Author-email: Adafruit Industries <circuitpython@adafruit.com>
License: MIT
Project-URL: Homepage, https://github.com/adafruit/Adafruit_CircuitPython_ConnectionManager
Keywords: adafruit,blinka,circuitpython,micropython,connectionmanager,sockets,networking
Classifier: Intended Audience :: Developers
Classifier: Topic :: Software Development :: Libraries
Classifier: Topic :: Software Development :: Embedded Systems
Classifier: Topic :: System :: Hardware
Classifier: License :: OSI Approved :: MIT License
Classifier: Programming Language :: Python :: 3
License-File: LICENSE
Requires-Dist: Adafruit-Blinka
Provides-Extra: optional
